{
  "repo": {
    "timestamp": 1782381688049
  },
  "packages": {
    "com.tristinbaker.idlefantasy": {
      "metadata": {
        "lastUpdated": 1782381665789
      },
      "versions": {
        "694997b40b6b70c4a5001c9e376ba58e89e7f5d2593b0a96f484d68f6af5612a": {
          "added": 1782381665789,
          "file": {
            "name": "/com.tristinbaker.idlefantasy_91.apk",
            "sha256": "694997b40b6b70c4a5001c9e376ba58e89e7f5d2593b0a96f484d68f6af5612a",
            "size": 5315474
          },
          "manifest": {
            "nativecode": [
              "arm64-v8a",
              "armeabi-v7a",
              "x86",
              "x86_64"
            ],
            "versionName": "1.9.15",
            "versionCode": 91,
            "usesSdk": {
              "minSdkVersion": 26,
              "targetSdkVersion": 35
            },
            "signer": {
              "sha256": [
                "99a980a934cb0149bfbdd5f4358471ffe69302e0467bae4d8574d4feeda34010"
              ]
            },
            "usesPermission": [
              {
                "name": "android.permission.POST_NOTIFICATIONS"
              },
              {
                "name": "android.permission.RECEIVE_BOOT_COMPLETED"
              },
              {
                "name": "android.permission.WAKE_LOCK"
              },
              {
                "name": "android.permission.USE_EXACT_ALARM"
              },
              {
                "name": "android.permission.SCHEDULE_EXACT_ALARM"
              },
              {
                "name": "com.tristinbaker.idlefantasy.DYNAMIC_RECEIVER_NOT_EXPORTED_PERMISSION"
              }
            ]
          },
          "whatsNew": {
            "en-US": "• Fix guild daily quest progress resetting mid-day when a new guild was unlocked; other guilds' progress is now preserved\n• Fix slayer weapon picker showing Attack pre-selected regardless of last-used weapon slot\n• Increase dark wizard spawn weight in Undead Crypt so slayer tasks complete more reliably\n• Fix enhanced potions being included in Sell Junk\n• Fix fish cooking quests appearing as crafting suggestions on non-fish cooking screens\n• Fix guild quest crafting suggestions showing locked que"
          }
        },
        "5f93eb35749a7bcf063c16fb2c3d43515a7668a46fd1bd32bad8ecb3621105fa": {
          "added": 1782208647617,
          "file": {
            "name": "/com.tristinbaker.idlefantasy_90.apk",
            "sha256": "5f93eb35749a7bcf063c16fb2c3d43515a7668a46fd1bd32bad8ecb3621105fa",
            "size": 5315062
          },
          "manifest": {
            "nativecode": [
              "arm64-v8a",
              "armeabi-v7a",
              "x86",
              "x86_64"
            ],
            "versionName": "1.9.14",
            "versionCode": 90,
            "usesSdk": {
              "minSdkVersion": 26,
              "targetSdkVersion": 35
            },
            "signer": {
              "sha256": [
                "99a980a934cb0149bfbdd5f4358471ffe69302e0467bae4d8574d4feeda34010"
              ]
            },
            "usesPermission": [
              {
                "name": "android.permission.POST_NOTIFICATIONS"
              },
              {
                "name": "android.permission.RECEIVE_BOOT_COMPLETED"
              },
              {
                "name": "android.permission.WAKE_LOCK"
              },
              {
                "name": "android.permission.USE_EXACT_ALARM"
              },
              {
                "name": "android.permission.SCHEDULE_EXACT_ALARM"
              },
              {
                "name": "com.tristinbaker.idlefantasy.DYNAMIC_RECEIVER_NOT_EXPORTED_PERMISSION"
              }
            ]
          },
          "whatsNew": {
            "en-US": "• Hard mode potion sequence now uses 8 colours (Yellow and Pink added) so all 8 colour buttons are visible\n• Indonesian (Bahasa Indonesia) now appears as a selectable language option in Settings\n"
          }
        },
        "23d61152f628fb924b81416da68018194b5df3e1517388fb68f0c08ab0047f77": {
          "added": 1782170008773,
          "file": {
            "name": "/com.tristinbaker.idlefantasy_89.apk",
            "sha256": "23d61152f628fb924b81416da68018194b5df3e1517388fb68f0c08ab0047f77",
            "size": 5314306
          },
          "manifest": {
            "nativecode": [
              "arm64-v8a",
              "armeabi-v7a",
              "x86",
              "x86_64"
            ],
            "versionName": "1.9.13",
            "versionCode": 89,
            "usesSdk": {
              "minSdkVersion": 26,
              "targetSdkVersion": 35
            },
            "signer": {
              "sha256": [
                "99a980a934cb0149bfbdd5f4358471ffe69302e0467bae4d8574d4feeda34010"
              ]
            },
            "usesPermission": [
              {
                "name": "android.permission.POST_NOTIFICATIONS"
              },
              {
                "name": "android.permission.RECEIVE_BOOT_COMPLETED"
              },
              {
                "name": "android.permission.WAKE_LOCK"
              },
              {
                "name": "android.permission.USE_EXACT_ALARM"
              },
              {
                "name": "android.permission.SCHEDULE_EXACT_ALARM"
              },
              {
                "name": "com.tristinbaker.idlefantasy.DYNAMIC_RECEIVER_NOT_EXPORTED_PERMISSION"
              }
            ]
          },
          "whatsNew": {
            "en-US": "• Slayer: Foretell queue now shows a \"+ Queue\" button on each row so you can manually queue that dungeon at any time\n• Carnival: Fairgrounds building upgrades now boost idle session ticket chance (+5%/+10%/+15% per tier)\n• Carnival: Difficulty setting for each minigame is now remembered across sessions\n• Carnival: Potion Sequence now uses 6 colours for both the sequence length and the button palette (Normal: remember 6, Hard: remember 8)\n• Guild dailies: Fletchers Guild no longer assigns arrow-c"
          }
        },
        "c33b8fe1badaceab2feffcaae3c3d47c4cb6c50355d33f6c1f7c65ebfda16863": {
          "added": 1782088156707,
          "file": {
            "name": "/com.tristinbaker.idlefantasy_88.apk",
            "sha256": "c33b8fe1badaceab2feffcaae3c3d47c4cb6c50355d33f6c1f7c65ebfda16863",
            "size": 5230894
          },
          "manifest": {
            "nativecode": [
              "arm64-v8a",
              "armeabi-v7a",
              "x86",
              "x86_64"
            ],
            "versionName": "1.9.12",
            "versionCode": 88,
            "usesSdk": {
              "minSdkVersion": 26,
              "targetSdkVersion": 35
            },
            "signer": {
              "sha256": [
                "99a980a934cb0149bfbdd5f4358471ffe69302e0467bae4d8574d4feeda34010"
              ]
            },
            "usesPermission": [
              {
                "name": "android.permission.POST_NOTIFICATIONS"
              },
              {
                "name": "android.permission.RECEIVE_BOOT_COMPLETED"
              },
              {
                "name": "android.permission.WAKE_LOCK"
              },
              {
                "name": "android.permission.USE_EXACT_ALARM"
              },
              {
                "name": "android.permission.SCHEDULE_EXACT_ALARM"
              },
              {
                "name": "com.tristinbaker.idlefantasy.DYNAMIC_RECEIVER_NOT_EXPORTED_PERMISSION"
              }
            ]
          },
          "whatsNew": {
            "en-US": "• Fix clearing a magic bean farming patch consuming the seed permanently; the seed is now returned and can be replanted\n• Fix bones quantity field in the prayer session sheet being too narrow to display large numbers"
          }
        },
        "75b88792d2018ed2d1d7f477c3b3b571de6b303fd4aadaada3c2a0bfdd1f733f": {
          "added": 1782037581339,
          "file": {
            "name": "/com.tristinbaker.idlefantasy_87.apk",
            "sha256": "75b88792d2018ed2d1d7f477c3b3b571de6b303fd4aadaada3c2a0bfdd1f733f",
            "size": 5230598
          },
          "manifest": {
            "nativecode": [
              "arm64-v8a",
              "armeabi-v7a",
              "x86",
              "x86_64"
            ],
            "versionName": "1.9.11",
            "versionCode": 87,
            "usesSdk": {
              "minSdkVersion": 26,
              "targetSdkVersion": 35
            },
            "signer": {
              "sha256": [
                "99a980a934cb0149bfbdd5f4358471ffe69302e0467bae4d8574d4feeda34010"
              ]
            },
            "usesPermission": [
              {
                "name": "android.permission.POST_NOTIFICATIONS"
              },
              {
                "name": "android.permission.RECEIVE_BOOT_COMPLETED"
              },
              {
                "name": "android.permission.WAKE_LOCK"
              },
              {
                "name": "android.permission.USE_EXACT_ALARM"
              },
              {
                "name": "android.permission.SCHEDULE_EXACT_ALARM"
              },
              {
                "name": "com.tristinbaker.idlefantasy.DYNAMIC_RECEIVER_NOT_EXPORTED_PERMISSION"
              }
            ]
          },
          "whatsNew": {
            "en-US": "• Fix agility prestige not reducing session time when starting a new session directly from the Skills screen\n• Fix worker efficiency multiplier incorrectly scaling crafting output (bars, planks, etc.) — efficiency now only applies to gathering\n• Fix bronze pickaxe disappearing from the Armory after selling; starting tools are always marked as found\n• Fix Hide Completed toggle resetting when leaving and returning to a Guild Hall screen\n• Fix gathering tool multipliers rounding incorrectly; iron p"
          }
        },
        "2d51c13133a9dd079169f2e4943d27ae392cfc2b61d812824821eed056542bde": {
          "added": 1781948661146,
          "file": {
            "name": "/com.tristinbaker.idlefantasy_86.apk",
            "sha256": "2d51c13133a9dd079169f2e4943d27ae392cfc2b61d812824821eed056542bde",
            "size": 5228062
          },
          "manifest": {
            "nativecode": [
              "arm64-v8a",
              "armeabi-v7a",
              "x86",
              "x86_64"
            ],
            "versionName": "1.9.10",
            "versionCode": 86,
            "usesSdk": {
              "minSdkVersion": 26,
              "targetSdkVersion": 35
            },
            "signer": {
              "sha256": [
                "99a980a934cb0149bfbdd5f4358471ffe69302e0467bae4d8574d4feeda34010"
              ]
            },
            "usesPermission": [
              {
                "name": "android.permission.POST_NOTIFICATIONS"
              },
              {
                "name": "android.permission.RECEIVE_BOOT_COMPLETED"
              },
              {
                "name": "android.permission.WAKE_LOCK"
              },
              {
                "name": "android.permission.USE_EXACT_ALARM"
              },
              {
                "name": "android.permission.SCHEDULE_EXACT_ALARM"
              },
              {
                "name": "com.tristinbaker.idlefantasy.DYNAMIC_RECEIVER_NOT_EXPORTED_PERMISSION"
              }
            ]
          },
          "whatsNew": {
            "en-US": "• Fix food overhealing display for prestiged Hitpoints players (simulator max HP now matches the HP bar)\n• Dungeons and boss fights now cap food consumption at 200 items per session (best-healing food used first); the difficulty indicator now runs the actual combat simulation for each dungeon (accounting for your attack and kill speed) instead of a defence-only estimate, so ratings reflect real survivability\n• Fix queue XP estimate from Skills tab not including pet bonuses, causing it to show le"
          }
        },
        "75ee3ac332de6335ee5849aee020f2a2f6bf067ebbad2c1810777289bba0673c": {
          "added": 1781911968232,
          "file": {
            "name": "/com.tristinbaker.idlefantasy_85.apk",
            "sha256": "75ee3ac332de6335ee5849aee020f2a2f6bf067ebbad2c1810777289bba0673c",
            "size": 5211066
          },
          "manifest": {
            "nativecode": [
              "arm64-v8a",
              "armeabi-v7a",
              "x86",
              "x86_64"
            ],
            "versionName": "1.9.9",
            "versionCode": 85,
            "usesSdk": {
              "minSdkVersion": 26,
              "targetSdkVersion": 35
            },
            "signer": {
              "sha256": [
                "99a980a934cb0149bfbdd5f4358471ffe69302e0467bae4d8574d4feeda34010"
              ]
            },
            "usesPermission": [
              {
                "name": "android.permission.POST_NOTIFICATIONS"
              },
              {
                "name": "android.permission.RECEIVE_BOOT_COMPLETED"
              },
              {
                "name": "android.permission.WAKE_LOCK"
              },
              {
                "name": "android.permission.USE_EXACT_ALARM"
              },
              {
                "name": "android.permission.SCHEDULE_EXACT_ALARM"
              },
              {
                "name": "com.tristinbaker.idlefantasy.DYNAMIC_RECEIVER_NOT_EXPORTED_PERMISSION"
              }
            ]
          },
          "whatsNew": {
            "en-US": "• Fix pet XP bonuses and prestige bonuses not applying to boss session rewards; both are now correctly applied when collecting a completed boss fight\n• Fix prestige XP bonus not applying to dungeon session rewards when collecting from either the Home or Combat screen\n• Fix \"combat\" pets (Dragon Whelp, Void Wisp) not counting toward the XP bonus applied during dungeon sessions; multiple combat pets now stack correctly\n• Fix worker cooking/crafting sheet showing English item names instead of the d"
          }
        },
        "a4b2c8e71d0f1e10bcce0d57854ceb79d0a9b836729174bda9ea0f9dfb39598a": {
          "added": 1781866406692,
          "file": {
            "name": "/com.tristinbaker.idlefantasy_84.apk",
            "sha256": "a4b2c8e71d0f1e10bcce0d57854ceb79d0a9b836729174bda9ea0f9dfb39598a",
            "size": 5210730
          },
          "manifest": {
            "nativecode": [
              "arm64-v8a",
              "armeabi-v7a",
              "x86",
              "x86_64"
            ],
            "versionName": "1.9.8",
            "versionCode": 84,
            "usesSdk": {
              "minSdkVersion": 26,
              "targetSdkVersion": 35
            },
            "signer": {
              "sha256": [
                "99a980a934cb0149bfbdd5f4358471ffe69302e0467bae4d8574d4feeda34010"
              ]
            },
            "usesPermission": [
              {
                "name": "android.permission.POST_NOTIFICATIONS"
              },
              {
                "name": "android.permission.RECEIVE_BOOT_COMPLETED"
              },
              {
                "name": "android.permission.WAKE_LOCK"
              },
              {
                "name": "android.permission.USE_EXACT_ALARM"
              },
              {
                "name": "android.permission.SCHEDULE_EXACT_ALARM"
              },
              {
                "name": "com.tristinbaker.idlefantasy.DYNAMIC_RECEIVER_NOT_EXPORTED_PERMISSION"
              }
            ]
          },
          "whatsNew": {
            "en-US": "• Workers can now be assigned Construction and Thieving tasks (previously showed Coming Soon or did nothing)\n• Agility moved to the Support Skills section in the Skills tab, consistent with the Profile and Guild Hall screens\n• Automatic backup now includes active sessions (same as manual Export) and no longer writes corrupted files when overwriting an existing backup\n• Release APK is now named IdleFantasy-v[version].apk so downloaded copies are easier to identify and archive\n• Fix toast for addi"
          }
        }
      }
    }
  }
}